eventhive/__init__.py
eventhive/__meta__.py
eventhive/broadcast.py
eventhive/cli.py
eventhive/config.py
eventhive/crypto.py
eventhive/exceptions.py
eventhive/logger.py
eventhive/connectors/__init__.py
eventhive/connectors/base.py
eventhive/connectors/fastapi_pubsub.py
eventhive/connectors/redis.py
eventhive/external/__init__.py
eventhive/external/aes.py
eventhive/servers/__init__.py
eventhive/servers/fastapi_srv.py
tests/__init__.py
tests/test_crypto.py
tests/test_fastapi.py
tests/test_redis.py
tests/test_zeroconf.py
eventhive-0.5.0.dist-info/LICENSE
eventhive-0.5.0.dist-info/METADATA
eventhive-0.5.0.dist-info/WHEEL
eventhive-0.5.0.dist-info/entry_points.txt
eventhive-0.5.0.dist-info/top_level.txt
eventhive-0.5.0.dist-info/zip-safe
eventhive-0.5.0.dist-info/RECORD
