Metadata-Version: 2.1
Name: eventhive
Version: 0.5.0
Summary: Network PubSub and Async Message Passing for Humans
Home-page: https://github.com/operatorequals/eventhive
Author: attr: eventhive.__meta__.__author__
Author-email: "john.torakis@gmail.com"
License: MIT
Keywords: pubsub,microservice,iot,rpc
Classifier: License :: OSI Approved :: MIT License
Classifier: Programming Language :: Python :: 3
License-File: LICENSE
Requires-Dist: hooker (>=1.0.2)
Requires-Dist: fastapi-websocket-pubsub (==0.3.1)
Requires-Dist: zeroconf (==0.47.4)
Requires-Dist: PyYAML (==6.0)
Requires-Dist: mergedeep (==1.3.4)
Requires-Dist: termcolor (==2.2.0)
Provides-Extra: dev
Requires-Dist: autopep8 (==2.0.2) ; extra == 'dev'
Requires-Dist: docker (==6.0.1) ; extra == 'dev'
Provides-Extra: redis
Requires-Dist: redis (>=4.5.1) ; extra == 'redis'
